promisedio/promise/__init__.py
promisedio/promise/capsule/promisedio/promise.h
promisedio/promise/clinic/promise.c.h
promisedio/promise/promise.c
promisedio/promise/_promise.cpython-310-darwin.so
promisedio/promise/_promise_debug.cpython-310-darwin.so
promisedio_promise-1.0.23.dist-info/LICENSE
promisedio_promise-1.0.23.dist-info/WHEEL
promisedio_promise-1.0.23.dist-info/METADATA
promisedio_promise-1.0.23.dist-info/RECORD
