Metadata-Version: 2.1
Name: promisedio-promise
Version: 1.0.23
Summary: High-performance promise implementation for Python
Home-page: https://github.com/promisedio/promise
License: MIT
Author: aachurin
Author-email: aachurin@gmail.com
Requires-Python: >=3.10,<4.0
Classifier: License :: OSI Approved :: MIT License
Classifier: Programming Language :: Python :: 3
Classifier: Programming Language :: Python :: 3.10
Classifier: Programming Language :: Python :: Implementation :: CPython
Project-URL: Repository, https://github.com/promisedio/promise
